{
  "updatedAt": "2026-07-15T02:54:48.335Z",
  "quotes": {
    "AAPL": {
      "symbol": "AAPL",
      "price": 314.86,
      "previousClose": 310.66,
      "changePct": 1.35,
      "currency": "USD",
      "source": "yahoo"
    },
    "MSFT": {
      "symbol": "MSFT",
      "price": 387.09,
      "previousClose": 388.84,
      "changePct": -0.45,
      "currency": "USD",
      "source": "yahoo"
    },
    "GOOGL": {
      "symbol": "GOOGL",
      "price": 359.51,
      "previousClose": 367.03,
      "changePct": -2.05,
      "currency": "USD",
      "source": "yahoo"
    }
  }
}
