{
  "updatedAt": "2026-07-13T22:36:49.910Z",
  "quotes": {
    "AAPL": {
      "symbol": "AAPL",
      "price": 317.31,
      "previousClose": 312.66,
      "changePct": 1.49,
      "currency": "USD",
      "source": "yahoo"
    },
    "MSFT": {
      "symbol": "MSFT",
      "price": 385.1,
      "previousClose": 390.49,
      "changePct": -1.38,
      "currency": "USD",
      "source": "yahoo"
    },
    "GOOGL": {
      "symbol": "GOOGL",
      "price": 352.51,
      "previousClose": 366.46,
      "changePct": -3.81,
      "currency": "USD",
      "source": "yahoo"
    }
  }
}
