{
  "updatedAt": "2026-07-01T15:47:32.383Z",
  "quotes": {
    "AAPL": {
      "symbol": "AAPL",
      "price": 294.89,
      "previousClose": 293.08,
      "changePct": 0.62,
      "currency": "USD",
      "source": "yahoo"
    },
    "MSFT": {
      "symbol": "MSFT",
      "price": 384.67,
      "previousClose": 365.46,
      "changePct": 5.26,
      "currency": "USD",
      "source": "yahoo"
    },
    "GOOGL": {
      "symbol": "GOOGL",
      "price": 359.67,
      "previousClose": 345.29,
      "changePct": 4.16,
      "currency": "USD",
      "source": "yahoo"
    }
  }
}
